{
  "title": "Headline Component Tests",
  "text": "Page for Headline component tests",
  "image": "https://picsum.photos/1440/720",
  "group": "hoi-component",
  "components": [
    {
      "type": "wrapper",
      "components": [
        {
          "type": "headline",
          "level": "1",
          "copy": "This is a headline 1"
        }
      ]
    },
    {
      "type": "spacer"
    },
    {
      "type": "wrapper",
      "components": [
        {
          "type": "headline",
          "level": "2",
          "copy": "This is a headline 2"
        }
      ]
    },
    {
      "type": "spacer"
    },
    {
      "type": "wrapper",
      "components": [
        {
          "type": "headline",
          "level": "3",
          "copy": "This is a headline 3"
        }
      ]
    },
    {
      "type": "spacer"
    },
    {
      "type": "wrapper",
      "components": [
        {
          "type": "headline",
          "level": "4",
          "copy": "This is a headline 4"
        }
      ]
    },
    {
      "type": "spacer"
    },
    {
      "type": "wrapper",
      "components": [
        {
          "type": "headline",
          "level": "5",
          "copy": "This is a headline 5"
        }
      ]
    },
    {
      "type": "spacer"
    },
    {
      "type": "wrapper",
      "components": [
        {
          "type": "headline",
          "level": "6",
          "copy": "This is a headline 6"
        }
      ]
    }
  ]
}
